supadata_langchain/__init__.py
supadata_langchain/loader.py
supadata_langchain-0.1.0.dist-info/METADATA
supadata_langchain-0.1.0.dist-info/WHEEL
supadata_langchain-0.1.0.dist-info/RECORD
