Metadata-Version: 2.4
Name: supadata-langchain
Version: 0.1.0
Summary: Supadata document loader integration for LangChain (Python)
Project-URL: Homepage, https://supadata.ai
Project-URL: Source, https://github.com/supadata-ai/langchain-py
Project-URL: Issues, https://github.com/supadata-ai/langchain-py/issues
Author: Mudassir
License: MIT
Classifier: Intended Audience :: Developers
Classifier: License :: OSI Approved :: MIT License
Classifier: Programming Language :: Python :: 3
Classifier: Programming Language :: Python :: 3.9
Classifier: Programming Language :: Python :: 3.10
Classifier: Programming Language :: Python :: 3.11
Classifier: Topic :: Scientific/Engineering :: Artificial Intelligence
Requires-Python: >=3.9
Requires-Dist: langchain-core>=0.3.0
Requires-Dist: supadata>=1.5.0
Provides-Extra: dev
Requires-Dist: mypy; extra == 'dev'
Requires-Dist: pytest; extra == 'dev'
Requires-Dist: pytest-asyncio; extra == 'dev'
Requires-Dist: ruff; extra == 'dev'
